LICENSE
README.md
setup.py
pyacad/APoint.py
pyacad/Autocad.py
pyacad/Types.py
pyacad/__init__.py
pyacad.egg-info/PKG-INFO
pyacad.egg-info/SOURCES.txt
pyacad.egg-info/dependency_links.txt
pyacad.egg-info/requires.txt
pyacad.egg-info/top_level.txt